odoo/addons/ssi_odoo_implementation/README.rst
odoo/addons/ssi_odoo_implementation/__init__.py
odoo/addons/ssi_odoo_implementation/__manifest__.py
odoo/addons/ssi_odoo_implementation/menu.xml
odoo/addons/ssi_odoo_implementation/approval_template/odoo_change_request.xml
odoo/addons/ssi_odoo_implementation/approval_template/odoo_configuration_change_record.xml
odoo/addons/ssi_odoo_implementation/approval_template/odoo_use_case_specification.xml
odoo/addons/ssi_odoo_implementation/data/approval_template_data.xml
odoo/addons/ssi_odoo_implementation/data/ir_sequence_data.xml
odoo/addons/ssi_odoo_implementation/data/policy_template_data.xml
odoo/addons/ssi_odoo_implementation/data/sequence_template_data.xml
odoo/addons/ssi_odoo_implementation/i18n/ssi_odoo_implementation.pot
odoo/addons/ssi_odoo_implementation/ir_sequence/odoo_change_request.xml
odoo/addons/ssi_odoo_implementation/ir_sequence/odoo_configuration_change_record.xml
odoo/addons/ssi_odoo_implementation/ir_sequence/odoo_deployment.xml
odoo/addons/ssi_odoo_implementation/ir_sequence/odoo_feature_implementation.xml
odoo/addons/ssi_odoo_implementation/ir_sequence/odoo_feature_issue.xml
odoo/addons/ssi_odoo_implementation/ir_sequence/odoo_implementation.xml
odoo/addons/ssi_odoo_implementation/ir_sequence/odoo_use_case_specification.xml
odoo/addons/ssi_odoo_implementation/models/__init__.py
odoo/addons/ssi_odoo_implementation/models/odoo_additional_functionality.py
odoo/addons/ssi_odoo_implementation/models/odoo_change_request.py
odoo/addons/ssi_odoo_implementation/models/odoo_configuration_change_record.py
odoo/addons/ssi_odoo_implementation/models/odoo_configuration_change_record_detail.py
odoo/addons/ssi_odoo_implementation/models/odoo_deployment.py
odoo/addons/ssi_odoo_implementation/models/odoo_deployment_new_feature.py
odoo/addons/ssi_odoo_implementation/models/odoo_environment.py
odoo/addons/ssi_odoo_implementation/models/odoo_feature.py
odoo14_addon_ssi_odoo_implementation-14.0.5.22.0.dist-info/METADATA
odoo14_addon_ssi_odoo_implementation-14.0.5.22.0.dist-info/WHEEL
odoo14_addon_ssi_odoo_implementation-14.0.5.22.0.dist-info/top_level.txt
odoo14_addon_ssi_odoo_implementation-14.0.5.22.0.dist-info/RECORD
